CppPythonSocket/__init__.py
CppPythonSocket/server.py
CppPythonSocket-0.2.2.dist-info/LICENCE
CppPythonSocket-0.2.2.dist-info/METADATA
CppPythonSocket-0.2.2.dist-info/WHEEL
CppPythonSocket-0.2.2.dist-info/top_level.txt
CppPythonSocket-0.2.2.dist-info/RECORD
