Metadata-Version: 2.1
Name: CppPythonSocket
Version: 0.2.2
Summary: Simple TCP/IP socket comunication wrapper between c++ and Python for IPC.
Home-page: https://github.com/OleguerCanal/cpp_python_socket.git
Author: OleguerCanal
Author-email: oleguer.canal@hotmail.com
License: UNKNOWN
Platform: UNKNOWN
Classifier: Programming Language :: Python :: 3
Classifier: License :: OSI Approved :: MIT License
Classifier: Operating System :: OS Independent
